discordify/__init__.py
discordify/emojify.py
discordify/spotify.py
discordify/font/spotify.ttf
discordify-0.1.2.dist-info/LICENSE
discordify-0.1.2.dist-info/METADATA
discordify-0.1.2.dist-info/WHEEL
discordify-0.1.2.dist-info/top_level.txt
discordify-0.1.2.dist-info/RECORD
