Metadata-Version: 2.1
Name: discordify
Version: 0.1.2
Summary: A Python package to retrieve detailed Spotify album images and emojify images for Discord integration.
Home-page: https://github.com/iayushanand/discordify
Author: Ayu Itz
Author-email: icontactayu@gmail.com
Keywords: discord spotify spotify-wrapper image
Classifier: Development Status :: 3 - Alpha
Classifier: Intended Audience :: Developers
Classifier: License :: OSI Approved :: MIT License
Classifier: Programming Language :: Python :: 3
Classifier: Operating System :: OS Independent
Requires-Python: >=3.6
License-File: LICENSE
Requires-Dist: discord.py ==2.3.2
Requires-Dist: pillow ==10.0.0
Requires-Dist: cbvx ==0.1.0
